.travis.yml
MANIFEST.in
README.rst
setup.py
docs/CHANGELOG.rst
docs/LICENSE.rst
docs/api.rst
docs/conf.py
docs/glossary.rst
docs/index.rst
docs/_static/.gitkeep
plonetrick/__init__.py
plonetrick.csrfworkarounds.egg-info/PKG-INFO
plonetrick.csrfworkarounds.egg-info/SOURCES.txt
plonetrick.csrfworkarounds.egg-info/dependency_links.txt
plonetrick.csrfworkarounds.egg-info/entry_points.txt
plonetrick.csrfworkarounds.egg-info/namespace_packages.txt
plonetrick.csrfworkarounds.egg-info/not-zip-safe
plonetrick.csrfworkarounds.egg-info/requires.txt
plonetrick.csrfworkarounds.egg-info/top_level.txt
plonetrick/csrfworkarounds/__init__.py
plonetrick/csrfworkarounds/configure.zcml
plonetrick/csrfworkarounds/testing.py
plonetrick/csrfworkarounds/browser/__init__.py
plonetrick/csrfworkarounds/browser/configure.zcml
plonetrick/csrfworkarounds/browser/disable_csrf_protection.py
plonetrick/csrfworkarounds/browser/tinymce.py
plonetrick/csrfworkarounds/tests/__init__.py
plonetrick/csrfworkarounds/tests/test_view.py