Metadata-Version: 1.1
Name: plonetrick.csrfworkarounds
Version: 0.9.0
Summary: plonetrick.csrfworkarounds
Home-page: http://pypi.python.org/pypi/plonetrick.csrfworkarounds
Author: Alessandro Pisa
Author-email: alessandro.pisa@gmail.com
License: GPL
Keywords: Plone
Platform: UNKNOWN
Classifier: Framework :: Plone
Classifier: Programming Language :: Python
Classifier: Programming Language :: Python
Classifier: Programming Language :: Python :: 2.6
Classifier: Programming Language :: Python :: 2.7
Classifier: License :: OSI Approved :: GNU General Public License (GPL)
